setup.py
ydtest/__init__.py
ydtest.egg-info/PKG-INFO
ydtest.egg-info/SOURCES.txt
ydtest.egg-info/dependency_links.txt
ydtest.egg-info/not-zip-safe
ydtest.egg-info/top_level.txt