Metadata-Version: 1.0
Name: ydtest
Version: 0.1
Summary: This is ydtest (yandong test) joke.
Home-page: UNKNOWN
Author: Yandong Qiao
Author-email: yandongqiao@gmail.com
License: UNKNOWN
Platform: UNKNOWN
